gawd/__init__.py
gawd/__main__.py
gawd-1.1.1.dist-info/LICENSE
gawd-1.1.1.dist-info/METADATA
gawd-1.1.1.dist-info/WHEEL
gawd-1.1.1.dist-info/entry_points.txt
gawd-1.1.1.dist-info/top_level.txt
gawd-1.1.1.dist-info/zip-safe
gawd-1.1.1.dist-info/RECORD
