Metadata-Version: 2.1
Name: gawd
Version: 1.1.1
Summary: GitHub Actions Workflow Differ
Home-page: https://github.com/pooya-rostami/gawd
Author: Pooya Rostami Mazrae, Alexandre Decan
License: LGPLv3
Keywords: github actions workflow diff change modification
Classifier: License :: OSI Approved :: GNU Lesser General Public License v3 (LGPLv3)
Classifier: Development Status :: 4 - Beta
Classifier: Intended Audience :: Developers
Classifier: Intended Audience :: Education
Classifier: Intended Audience :: Information Technology
Classifier: Intended Audience :: Science/Research
Classifier: Programming Language :: Python :: 3 :: Only
Classifier: Programming Language :: Python :: 3.8
Classifier: Programming Language :: Python :: 3.9
Classifier: Programming Language :: Python :: 3.10
Classifier: Programming Language :: Python :: 3.11
Classifier: Programming Language :: Python :: 3.12
Requires-Python: ~= 3.8
License-File: LICENSE
Requires-Dist: ruamel.yaml ~=0.18
Provides-Extra: test
Requires-Dist: pytest ~=7.0 ; extra == 'test'
